[
  {
    "platform": "reddit",
    "text": "Should i join polaris school of technology? Is it better than other ...",
    "url": "https://www.reddit.com/r/Btechtards/comments/1edc645/should_i_join_polaris_school_of_technology_is_it/",
    "date": "2026-04-19T11:52:52.841698+00:00",
    "sentiment": "neutral",
    "score": 0,
    "impressions": 8500
  },
  {
    "platform": "reddit",
    "text": "Can someone actually drop a year and join Polaris School ... - Reddit",
    "url": "https://www.reddit.com/r/CollegeDropouts/comments/1kijbpj/can_someone_actually_drop_a_year_and_join_polaris/",
    "date": "2026-04-19T11:52:52.841723+00:00",
    "sentiment": "neutral",
    "score": 0,
    "impressions": 4500
  },
  {
    "platform": "reddit",
    "text": "Should I join Polaris school of technology? : r/Btechtards - Reddit",
    "url": "https://www.reddit.com/r/Btechtards/comments/1ktg5te/should_i_join_polaris_school_of_technology/",
    "date": "2026-04-19T11:52:52.841730+00:00",
    "sentiment": "neutral",
    "score": 0,
    "impressions": 2800
  },
  {
    "platform": "reddit",
    "text": "Ive seen a lot of good things about Polaris School of Technology ...",
    "url": "https://www.reddit.com/r/Students/comments/1jw0uev/ive_seen_a_lot_of_good_things_about_polaris/",
    "date": "2026-04-19T11:52:52.841735+00:00",
    "sentiment": "positive",
    "score": 1,
    "impressions": 1900
  },
  {
    "platform": "reddit",
    "text": "Polaris School of Technology vs Intellipaat School of ... - Reddit",
    "url": "https://www.reddit.com/r/courselearning/comments/1otlv74/polaris_school_of_technology_vs_intellipaat/",
    "date": "2026-04-19T11:52:52.841741+00:00",
    "sentiment": "neutral",
    "score": 0,
    "impressions": 1400
  },
  {
    "platform": "reddit",
    "text": "What are your thoughts on Polaris school of technology? - Reddit",
    "url": "https://www.reddit.com/r/Btechtards/comments/1kyveyt/what_are_your_thoughts_on_polaris_school_of/",
    "date": "2026-04-19T11:52:52.841745+00:00",
    "sentiment": "neutral",
    "score": 0,
    "impressions": 1100
  },
  {
    "platform": "reddit",
    "text": "Polaris School of Technology vs Newton School ! Which one best?",
    "url": "https://www.reddit.com/r/collegecompare/comments/1rwwrxi/polaris_school_of_technology_vs_newton_school/",
    "date": "2026-04-19T11:52:52.841750+00:00",
    "sentiment": "positive",
    "score": 1,
    "impressions": 900
  },
  {
    "platform": "reddit",
    "text": "Polaris School of Technology vs Scaler School of ... - Reddit",
    "url": "https://www.reddit.com/r/CollegeAdmissions/comments/1rcaw1o/polaris_school_of_technology_vs_scaler_school_of/",
    "date": "2026-04-19T11:52:52.841757+00:00",
    "sentiment": "neutral",
    "score": 0,
    "impressions": 750
  },
  {
    "platform": "reddit",
    "text": "Got jee advance rank 31XX, Going to join Polaris school of ... - Reddit",
    "url": "https://www.reddit.com/r/Btechtards/comments/1lqxtoe/got_jee_advance_rank_31xx_going_to_join_polaris/",
    "date": "2026-04-19T11:52:52.841763+00:00",
    "sentiment": "neutral",
    "score": 0,
    "impressions": 600
  },
  {
    "platform": "reddit",
    "text": "r/JEENEETards on Reddit: Polaris School Of Technology vs. Scaler ...",
    "url": "https://www.reddit.com/r/JEENEETards/comments/1lf4ypb/polaris_school_of_technology_vs_scaler_school_of/?tl=en",
    "date": "2026-04-19T11:52:52.841768+00:00",
    "sentiment": "neutral",
    "score": 0,
    "impressions": 500
  },
  {
    "platform": "reddit",
    "text": "Union Pizza Party at Polaris Campus : r/JPMorganChase - Reddit",
    "url": "https://www.reddit.com/r/JPMorganChase/comments/1kcg56k/union_pizza_party_at_polaris_campus/",
    "date": "2026-04-19T11:52:54.452068+00:00",
    "sentiment": "neutral",
    "score": 0,
    "impressions": 4500
  },
  {
    "platform": "reddit",
    "text": "Lost Ring - JPM Polaris Campus : r/Columbus - Reddit",
    "url": "https://www.reddit.com/r/Columbus/comments/15tzhzs/lost_ring_jpm_polaris_campus/",
    "date": "2026-04-19T11:52:54.452074+00:00",
    "sentiment": "neutral",
    "score": 0,
    "impressions": 2800
  },
  {
    "platform": "reddit",
    "text": "Chase RTO- Not enough parking : r/Columbus - Reddit",
    "url": "https://www.reddit.com/r/Columbus/comments/1jetyat/chase_rto_not_enough_parking/",
    "date": "2026-04-19T11:52:54.452078+00:00",
    "sentiment": "neutral",
    "score": 0,
    "impressions": 1900
  },
  {
    "platform": "reddit",
    "text": "Do you all have friends at work? : r/JPMorganChase - Reddit",
    "url": "https://www.reddit.com/r/JPMorganChase/comments/1r9770o/do_you_all_have_friends_at_work/",
    "date": "2026-04-19T11:52:54.452082+00:00",
    "sentiment": "neutral",
    "score": 0,
    "impressions": 1400
  },
  {
    "platform": "reddit",
    "text": "Experience Easter Weekend at Rock City (You are Invited!) - Reddit",
    "url": "https://www.reddit.com/r/cbusohio/comments/1k1qd3j/experience_easter_weekend_at_rock_city_you_are/",
    "date": "2026-04-19T11:52:54.452087+00:00",
    "sentiment": "neutral",
    "score": 0,
    "impressions": 1100
  },
  {
    "platform": "reddit",
    "text": "Chicago vs Columbus : r/JPMorganChase - Reddit",
    "url": "https://www.reddit.com/r/JPMorganChase/comments/1ozspus/chicago_vs_columbus/",
    "date": "2026-04-19T11:52:54.452090+00:00",
    "sentiment": "neutral",
    "score": 0,
    "impressions": 900
  },
  {
    "platform": "reddit",
    "text": "Road to Factoria Transfer Station trashed : r/BellevueWA - Reddit",
    "url": "https://www.reddit.com/r/BellevueWA/comments/1h30yfr/road_to_factoria_transfer_station_trashed/",
    "date": "2026-04-19T11:52:54.452095+00:00",
    "sentiment": "neutral",
    "score": 0,
    "impressions": 750
  },
  {
    "platform": "reddit",
    "text": "\u0e1b\u0e32\u0e23\u0e4c\u0e15\u0e35\u0e49\u0e1e\u0e34\u0e0b\u0e0b\u0e48\u0e32\u0e41\u0e2b\u0e48\u0e07\u0e04\u0e27\u0e32\u0e21\u0e2a\u0e32\u0e21\u0e31\u0e04\u0e04\u0e35\u0e17\u0e35\u0e48 Polaris Campus : r/JPMorganChase",
    "url": "https://www.reddit.com/r/JPMorganChase/comments/1kcg56k/union_pizza_party_at_polaris_campus/?tl=th",
    "date": "2026-04-19T11:52:54.452102+00:00",
    "sentiment": "neutral",
    "score": 0,
    "impressions": 600
  },
  {
    "platform": "reddit",
    "text": "r/Columbus on Reddit: Chase CEO tells employees they should quit ...",
    "url": "https://www.reddit.com/r/Columbus/comments/1j0ofzu/chase_ceo_tells_employees_they_should_quit_if/",
    "date": "2026-04-19T11:52:54.452107+00:00",
    "sentiment": "neutral",
    "score": 0,
    "impressions": 500
  },
  {
    "platform": "quora",
    "text": "What is the reputation of Polaris School of Technology for ... - Quora",
    "url": "https://www.quora.com/What-is-the-reputation-of-Polaris-School-of-Technology-for-engineering-degrees-Is-it-recommended-to-attend-this-college",
    "date": "2026-04-19T11:53:17.284024+00:00",
    "sentiment": "neutral",
    "score": 0,
    "impressions": 8500
  },
  {
    "platform": "quora",
    "text": "Is it worth attending Polaris School of Technology after ... - Quora",
    "url": "https://www.quora.com/Is-it-worth-attending-Polaris-School-of-Technology-after-seeing-the-recent-YouTube-reviews",
    "date": "2026-04-19T11:53:17.284044+00:00",
    "sentiment": "neutral",
    "score": 0,
    "impressions": 4500
  },
  {
    "platform": "quora",
    "text": "Is the Polaris School of Tech better than Scaler? - Quora",
    "url": "https://www.quora.com/Is-the-Polaris-School-of-Tech-better-than-Scaler",
    "date": "2026-04-19T11:53:17.284049+00:00",
    "sentiment": "neutral",
    "score": 0,
    "impressions": 2800
  },
  {
    "platform": "quora",
    "text": "How many programs does Polaris School of Technology actually ...",
    "url": "https://www.quora.com/How-many-programs-does-Polaris-School-of-Technology-actually-offer-and-are-all-of-them-under-B-Tech-CSE-or-are-there-separate-degrees",
    "date": "2026-04-19T11:53:17.284054+00:00",
    "sentiment": "neutral",
    "score": 0,
    "impressions": 1900
  },
  {
    "platform": "quora",
    "text": "How is Polaris School of Technology for a BTech? What are ... - Quora",
    "url": "https://www.quora.com/How-is-Polaris-School-of-Technology-for-a-BTech-What-are-the-pros-cons-of-joining-will-it-be-a-good-decision-for-me-to-join",
    "date": "2026-04-19T11:53:17.284058+00:00",
    "sentiment": "neutral",
    "score": 0,
    "impressions": 1400
  },
  {
    "platform": "quora",
    "text": "Polaris School of Technology PST - Quora",
    "url": "https://www.quora.com/profile/Polaris-School-of-Technology-PST",
    "date": "2026-04-19T11:53:17.284062+00:00",
    "sentiment": "neutral",
    "score": 0,
    "impressions": 1100
  },
  {
    "platform": "quora",
    "text": "How is Polaris School of Technology different from Newton ... - Quora",
    "url": "https://www.quora.com/How-is-Polaris-School-of-Technology-different-from-Newton-School-of-Technology-and-Scaler-School-of-Technology-Which-one-is-actually-worth-it-for-a-CS-career",
    "date": "2026-04-19T11:53:17.284067+00:00",
    "sentiment": "neutral",
    "score": 0,
    "impressions": 900
  },
  {
    "platform": "quora",
    "text": "Is Polaris School of Technology better than Symbiosis IoT Pune?",
    "url": "https://www.quora.com/Is-Polaris-School-of-Technology-better-than-Symbiosis-IoT-Pune",
    "date": "2026-04-19T11:53:17.284071+00:00",
    "sentiment": "neutral",
    "score": 0,
    "impressions": 750
  },
  {
    "platform": "quora",
    "text": "How is Polaris School of Technology for a BTech? What are the pros ...",
    "url": "https://ksthefutureofeducation.quora.com/https-www-quora-com-How-is-Polaris-School-of-Technology-for-a-BTech-What-are-the-pros-cons-of-joining-will-it-be-a-goo",
    "date": "2026-04-19T11:53:17.284075+00:00",
    "sentiment": "neutral",
    "score": 0,
    "impressions": 600
  },
  {
    "platform": "quora",
    "text": "What are the benefits of studying for a BTech degree at Polaris ...",
    "url": "https://www.quora.com/What-are-the-benefits-of-studying-for-a-BTech-degree-at-Polaris-School-of-Technology",
    "date": "2026-04-19T11:53:17.284079+00:00",
    "sentiment": "neutral",
    "score": 0,
    "impressions": 500
  },
  {
    "platform": "quora",
    "text": "What is campus life actually like at Polaris? Is the sci-fi lab ... - Quora",
    "url": "https://www.quora.com/What-is-campus-life-actually-like-at-Polaris-Is-the-sci-fi-lab-and-hackathon-thing-real",
    "date": "2026-04-19T11:53:18.975192+00:00",
    "sentiment": "neutral",
    "score": 0,
    "impressions": 8500
  },
  {
    "platform": "quora",
    "text": "What is the syllabus and test pattern for Virtusa Polaris in written ...",
    "url": "https://www.quora.com/What-is-the-syllabus-and-test-pattern-for-Virtusa-Polaris-in-written-exam",
    "date": "2026-04-19T11:53:18.975215+00:00",
    "sentiment": "neutral",
    "score": 0,
    "impressions": 4500
  },
  {
    "platform": "quora",
    "text": "Which top internet companies are not American? Is there a single ...",
    "url": "https://www.quora.com/Which-top-internet-companies-are-not-American-Is-there-a-single-Indian-company-in-the-list",
    "date": "2026-04-19T11:53:18.975223+00:00",
    "sentiment": "positive",
    "score": 1,
    "impressions": 2800
  },
  {
    "platform": "quora",
    "text": "Which is the most famous Indian technology? - Quora",
    "url": "https://www.quora.com/Which-is-the-most-famous-Indian-technology",
    "date": "2026-04-19T11:53:18.975228+00:00",
    "sentiment": "neutral",
    "score": 0,
    "impressions": 1900
  },
  {
    "platform": "quora",
    "text": "Why doesn't India have a famous international technology company?",
    "url": "https://www.quora.com/Why-doesnt-India-have-a-famous-international-technology-company",
    "date": "2026-04-19T11:53:18.975233+00:00",
    "sentiment": "neutral",
    "score": 0,
    "impressions": 1400
  },
  {
    "platform": "quora",
    "text": "What are the world wide famous Indian owned companies ? - Quora",
    "url": "https://www.quora.com/What-are-the-world-wide-famous-Indian-owned-companies",
    "date": "2026-04-19T11:53:18.975241+00:00",
    "sentiment": "neutral",
    "score": 0,
    "impressions": 1100
  },
  {
    "platform": "quora",
    "text": "Which are the top 20 companies in Pune by revenue? - Quora",
    "url": "https://www.quora.com/Which-are-the-top-20-companies-in-Pune-by-revenue",
    "date": "2026-04-19T11:53:18.975245+00:00",
    "sentiment": "positive",
    "score": 1,
    "impressions": 900
  },
  {
    "platform": "quora",
    "text": "Sourabh Mudiya - Quora",
    "url": "https://www.quora.com/profile/Sourabh-Mudiya",
    "date": "2026-04-19T11:53:22.630836+00:00",
    "sentiment": "neutral",
    "score": 0,
    "impressions": 8500
  },
  {
    "platform": "medium",
    "text": "What It's Really Like Studying at Polaris School of Technology ...",
    "url": "https://medium.com/@guptashilpaa8/what-its-really-like-studying-at-polaris-school-of-technology-student-perspective-e7282c1473dd",
    "date": "2026-04-19T11:53:24.420268+00:00",
    "sentiment": "neutral",
    "score": 0,
    "impressions": 8500
  },
  {
    "platform": "medium",
    "text": "Polaris School of Technology (PST) vs. Scaler & Newton - Medium",
    "url": "https://medium.com/@guptashilpaa8/polaris-school-of-technology-pst-vs-scaler-vs-newton-why-a-living-syllabus-matters-in-2025-f135dc014695",
    "date": "2026-04-19T11:53:24.420287+00:00",
    "sentiment": "neutral",
    "score": 0,
    "impressions": 4500
  },
  {
    "platform": "medium",
    "text": "Polaris School of Technology vs Scaler & Newton: Year-1 Wins",
    "url": "https://medium.com/@guptashilpaa8/why-i-stopped-worrying-about-placements-the-polaris-pst-outcome-engine-80d7a31ea6ef",
    "date": "2026-04-19T11:53:24.420293+00:00",
    "sentiment": "neutral",
    "score": 0,
    "impressions": 2800
  },
  {
    "platform": "medium",
    "text": "Is the Traditional B.Tech Dead? Why I Trashed My Tier-1 Seat for the ...",
    "url": "https://medium.com/@vihaanbal549/is-the-traditional-b-tech-dead-why-i-trashed-my-tier-1-seat-for-the-polaris-model-8df1ee2b7f06",
    "date": "2026-04-19T11:53:24.420298+00:00",
    "sentiment": "neutral",
    "score": 0,
    "impressions": 1900
  },
  {
    "platform": "medium",
    "text": "Why I Chose a \u201cWork-Integrated\u201d B.Tech Over a Traditional ...",
    "url": "https://medium.com/@piyushrawal2026/why-i-chose-a-work-integrated-b-tech-over-a-traditional-engineering-degree-fe29a6f349e0",
    "date": "2026-04-19T11:53:24.420305+00:00",
    "sentiment": "neutral",
    "score": 0,
    "impressions": 1400
  },
  {
    "platform": "medium",
    "text": "A Beginner's Guide to Containerization with Docker | by Shilpa ...",
    "url": "https://medium.com/@guptashilpaa8/a-beginners-guide-to-containerization-with-docker-20fe06c8d9cb",
    "date": "2026-04-19T11:53:24.420310+00:00",
    "sentiment": "neutral",
    "score": 0,
    "impressions": 1100
  },
  {
    "platform": "medium",
    "text": "GSoC 2025: My Journey into Open Source Begins - Nivedita - Medium",
    "url": "https://medium.com/@niveditachhokar/gsoc-2025-my-journey-into-open-source-begins-5ff4be5400c1",
    "date": "2026-04-19T11:53:24.420314+00:00",
    "sentiment": "neutral",
    "score": 0,
    "impressions": 900
  },
  {
    "platform": "medium",
    "text": "Why System.out.print() Causes TLE for Large Input and Output",
    "url": "https://medium.com/@ramoliyayug55/why-system-out-print-causes-tle-for-large-input-and-output-1f1ec02da642",
    "date": "2026-04-19T11:53:24.420318+00:00",
    "sentiment": "neutral",
    "score": 0,
    "impressions": 750
  },
  {
    "platform": "medium",
    "text": "2 following - Medium",
    "url": "https://medium.com/@polarisschooloftechnology/following",
    "date": "2026-04-19T11:53:24.420322+00:00",
    "sentiment": "neutral",
    "score": 0,
    "impressions": 600
  },
  {
    "platform": "medium",
    "text": "Closing the Tech Skill Gap: What Colleges Must Teach (But Often ...",
    "url": "https://medium.com/@priyankkapoor0108/closing-the-tech-skill-gap-what-colleges-must-teach-but-often-dont-ea90dc522462",
    "date": "2026-04-19T11:53:24.420326+00:00",
    "sentiment": "neutral",
    "score": 0,
    "impressions": 500
  },
  {
    "platform": "portal",
    "text": "Polaris School of Technology: Courses, Fees, Admission 2026 ...",
    "url": "https://www.shiksha.com/college/polaris-school-of-technology-electronic-city-bangalore-238876",
    "date": "2026-04-19T11:53:31.422508+00:00",
    "sentiment": "neutral",
    "score": 0,
    "impressions": 8500
  },
  {
    "platform": "portal",
    "text": "Polaris School of Technology Reviews on Placements, Faculty ...",
    "url": "https://www.shiksha.com/college/polaris-school-of-technology-electronic-city-bangalore-238876/reviews",
    "date": "2026-04-19T11:53:31.422527+00:00",
    "sentiment": "neutral",
    "score": 0,
    "impressions": 4500
  },
  {
    "platform": "portal",
    "text": "Polaris School of Technology Photos & Videos - Shiksha",
    "url": "https://www.shiksha.com/college/polaris-school-of-technology-electronic-city-bangalore-238876/gallery",
    "date": "2026-04-19T11:53:31.422532+00:00",
    "sentiment": "neutral",
    "score": 0,
    "impressions": 2800
  },
  {
    "platform": "portal",
    "text": "Polaris School of Technology B.Tech Courses & Fees 2026",
    "url": "https://www.shiksha.com/college/polaris-school-of-technology-electronic-city-bangalore-238876/courses/be-btech-bc",
    "date": "2026-04-19T11:53:31.422537+00:00",
    "sentiment": "neutral",
    "score": 0,
    "impressions": 1900
  },
  {
    "platform": "portal",
    "text": "Polaris School of Technology Admissions 2026: Fees, Eligibility ...",
    "url": "https://www.shiksha.com/college/polaris-school-of-technology-electronic-city-bangalore-238876/admission",
    "date": "2026-04-19T11:53:31.422541+00:00",
    "sentiment": "neutral",
    "score": 0,
    "impressions": 1400
  },
  {
    "platform": "portal",
    "text": "Polaris School of Technology Placements 2025: Highest Package ...",
    "url": "https://www.shiksha.com/college/polaris-school-of-technology-electronic-city-bangalore-238876/placement",
    "date": "2026-04-19T11:53:31.422545+00:00",
    "sentiment": "neutral",
    "score": 0,
    "impressions": 1100
  },
  {
    "platform": "portal",
    "text": "Polaris School of Technology Latest News & Notifications 2026",
    "url": "https://www.shiksha.com/college/polaris-school-of-technology-electronic-city-bangalore-238876/news-articles",
    "date": "2026-04-19T11:53:31.422549+00:00",
    "sentiment": "neutral",
    "score": 0,
    "impressions": 900
  },
  {
    "platform": "portal",
    "text": "Polaris School of Technology Faculty: Top Courses ... - Shiksha.com",
    "url": "https://www.shiksha.com/college/polaris-school-of-technology-electronic-city-bangalore-238876/faculty",
    "date": "2026-04-19T11:53:31.422554+00:00",
    "sentiment": "positive",
    "score": 1,
    "impressions": 750
  },
  {
    "platform": "portal",
    "text": "How to take admission in Polaris School of Technology?",
    "url": "https://ask.shiksha.com/how-to-take-admission-in-polaris-school-of-technology-qna-12738337",
    "date": "2026-04-19T11:53:31.422559+00:00",
    "sentiment": "neutral",
    "score": 0,
    "impressions": 600
  },
  {
    "platform": "portal",
    "text": "Page 4 - Polaris School of Technology - Shiksha.com",
    "url": "https://www.shiksha.com/tags/polaris-school-of-technology-tdp-2933294-4",
    "date": "2026-04-19T11:53:31.422563+00:00",
    "sentiment": "neutral",
    "score": 0,
    "impressions": 500
  },
  {
    "platform": "portal",
    "text": "B.Tech. in Information Technology at MLR Institute of ... - Shiksha.com",
    "url": "https://www.shiksha.com/college/mlr-institute-of-technology-jeedimetla-hyderabad-25370/course-b-tech-in-information-technology-75369",
    "date": "2026-04-19T11:53:33.209451+00:00",
    "sentiment": "neutral",
    "score": 0,
    "impressions": 8500
  },
  {
    "platform": "portal",
    "text": "Polaris School of Technology - Shiksha.com",
    "url": "https://www.shiksha.com/tags/polaris-school-of-technology-tdp-2933294-5",
    "date": "2026-04-19T11:53:36.587256+00:00",
    "sentiment": "neutral",
    "score": 0,
    "impressions": 2800
  },
  {
    "platform": "portal",
    "text": "Can I take admission in Polaris School of Technology BTech without ...",
    "url": "https://ask.shiksha.com/can-i-take-admission-in-polaris-school-of-technology-btech-without-pat-qna-11273656",
    "date": "2026-04-19T11:53:36.587261+00:00",
    "sentiment": "neutral",
    "score": 0,
    "impressions": 1900
  },
  {
    "platform": "portal",
    "text": "Polaris School of Technology Bangalore: Admission 2026, Fees ...",
    "url": "https://collegedunia.com/college/64976-polaris-school-of-technology-pst-bangalore",
    "date": "2026-04-19T11:53:38.579012+00:00",
    "sentiment": "neutral",
    "score": 0,
    "impressions": 8500
  },
  {
    "platform": "portal",
    "text": "Polaris School of Technology Courses & Fees 2026 - Collegedunia",
    "url": "https://collegedunia.com/college/64976-polaris-school-of-technology-pst-bangalore/courses-fees",
    "date": "2026-04-19T11:53:38.579031+00:00",
    "sentiment": "neutral",
    "score": 0,
    "impressions": 4500
  },
  {
    "platform": "portal",
    "text": "Polaris School of Technology Reviews on Placements, Faculty and ...",
    "url": "https://collegedunia.com/college/64976-polaris-school-of-technology-pst-bangalore/reviews",
    "date": "2026-04-19T11:53:38.579037+00:00",
    "sentiment": "neutral",
    "score": 0,
    "impressions": 2800
  },
  {
    "platform": "portal",
    "text": "Polaris School of Technology News and Latest Updates 2026",
    "url": "https://collegedunia.com/college/64976-polaris-school-of-technology-pst-bangalore/news",
    "date": "2026-04-19T11:53:38.579042+00:00",
    "sentiment": "neutral",
    "score": 0,
    "impressions": 1900
  },
  {
    "platform": "portal",
    "text": "Polaris School of Technology Placement 2026: Highest Package ...",
    "url": "https://collegedunia.com/college/64976-polaris-school-of-technology-pst-bangalore/placement",
    "date": "2026-04-19T11:53:38.579046+00:00",
    "sentiment": "neutral",
    "score": 0,
    "impressions": 1400
  },
  {
    "platform": "portal",
    "text": "Polaris School of Technology Gallery - Collegedunia",
    "url": "https://collegedunia.com/college/64976-polaris-school-of-technology-pst-bangalore/gallery",
    "date": "2026-04-19T11:53:38.579050+00:00",
    "sentiment": "neutral",
    "score": 0,
    "impressions": 1100
  },
  {
    "platform": "portal",
    "text": "Polaris School of Technology Faculty - Collegedunia",
    "url": "https://collegedunia.com/college/64976-polaris-school-of-technology-pst-bangalore/faculty",
    "date": "2026-04-19T11:53:38.579054+00:00",
    "sentiment": "neutral",
    "score": 0,
    "impressions": 900
  },
  {
    "platform": "portal",
    "text": "Polaris School of Technology Hostel Fees 2026, Facilities, Rooms ...",
    "url": "https://collegedunia.com/college/64976-polaris-school-of-technology-pst-bangalore/hostel",
    "date": "2026-04-19T11:53:38.579058+00:00",
    "sentiment": "neutral",
    "score": 0,
    "impressions": 750
  },
  {
    "platform": "portal",
    "text": "Polaris School of Technology B.Tech Computer Science and ...",
    "url": "https://collegedunia.com/college/64976-polaris-school-of-technology-pst-bangalore/bachelor-of-technology-btech-computer-science-and-engineering-artificial-intelligence-and-machine-learning-26456",
    "date": "2026-04-19T11:53:38.579062+00:00",
    "sentiment": "neutral",
    "score": 0,
    "impressions": 600
  },
  {
    "platform": "portal",
    "text": "PST Bangalore Course Admissions 2026: Dates, Courses, Fees ...",
    "url": "https://collegedunia.com/college/64976-polaris-school-of-technology-pst-bangalore/admission",
    "date": "2026-04-19T11:53:38.579066+00:00",
    "sentiment": "neutral",
    "score": 0,
    "impressions": 500
  },
  {
    "platform": "portal",
    "text": "Polaris school of technology When they call for entrance exam",
    "url": "https://www.careers360.com/question-polaris-school-of-technology-when-they-call-for-entrance-exam",
    "date": "2026-04-19T11:53:45.167634+00:00",
    "sentiment": "neutral",
    "score": 0,
    "impressions": 8500
  },
  {
    "platform": "portal",
    "text": "Is Scalar school of technology good option for cse - Careers360",
    "url": "https://www.careers360.com/question-is-scalar-school-of-technology-good-option-for-cse",
    "date": "2026-04-19T11:53:45.167655+00:00",
    "sentiment": "positive",
    "score": 1,
    "impressions": 4500
  },
  {
    "platform": "portal",
    "text": "Is newton school of technology best for BTech - Careers360",
    "url": "https://www.careers360.com/question-is-newton-school-of-technology-best-for-btech",
    "date": "2026-04-19T11:53:45.167661+00:00",
    "sentiment": "positive",
    "score": 1,
    "impressions": 2800
  },
  {
    "platform": "portal",
    "text": "when will the entrance exam in school of excellence - Careers360",
    "url": "https://www.careers360.com/question-when-will-the-entrance-exam-in-school-of-excellence",
    "date": "2026-04-19T11:53:45.167666+00:00",
    "sentiment": "neutral",
    "score": 0,
    "impressions": 1900
  },
  {
    "platform": "portal",
    "text": "MLRIT Dundigal Reviews on Placements, Courses, Faculty & Facilities",
    "url": "https://www.careers360.com/colleges/mlr-institute-of-technology-dundigal/reviews",
    "date": "2026-04-19T11:53:46.969428+00:00",
    "sentiment": "neutral",
    "score": 0,
    "impressions": 8500
  },
  {
    "platform": "web",
    "text": "Polaris School of Technology - BTech AI, PM & Cloud Engineering ...",
    "url": "https://polariscampus.com/",
    "date": "2026-04-19T11:53:52.332961+00:00",
    "sentiment": "neutral",
    "score": 0,
    "impressions": 8500
  },
  {
    "platform": "web",
    "text": "Polaris School of Technology (@polariscampus) - Instagram",
    "url": "https://www.instagram.com/polariscampus/?hl=en",
    "date": "2026-04-19T11:53:52.332986+00:00",
    "sentiment": "negative",
    "score": -1,
    "impressions": 2800
  },
  {
    "platform": "web",
    "text": "Polaris School of Technology Admissions Open 2026",
    "url": "https://polariscampus.com/admissions",
    "date": "2026-04-19T11:53:52.332991+00:00",
    "sentiment": "neutral",
    "score": 0,
    "impressions": 1900
  },
  {
    "platform": "web",
    "text": "All About POLARIS School Of Technology | Harsh sir - YouTube",
    "url": "https://www.youtube.com/watch?v=L9hDRe4vtHY",
    "date": "2026-04-19T11:53:52.333000+00:00",
    "sentiment": "neutral",
    "score": 0,
    "impressions": 1100
  },
  {
    "platform": "web",
    "text": "Polaris School of Technology Full Review | PAT 2025 - YouTube",
    "url": "https://www.youtube.com/watch?v=mlkt-lU5mPU",
    "date": "2026-04-19T11:53:52.333012+00:00",
    "sentiment": "neutral",
    "score": 0,
    "impressions": 750
  },
  {
    "platform": "web",
    "text": "Polaris School of Technology: Admission 2026, Courses, Fees ...",
    "url": "https://www.collegedekho.com/colleges/polaris-school-of-technology",
    "date": "2026-04-19T11:53:52.333016+00:00",
    "sentiment": "neutral",
    "score": 0,
    "impressions": 600
  },
  {
    "platform": "web",
    "text": "FUTURISTIC Campus of Polaris School of Technology in 2025!",
    "url": "https://www.youtube.com/watch?v=CllT0z0NkhM",
    "date": "2026-04-19T11:53:52.333020+00:00",
    "sentiment": "neutral",
    "score": 0,
    "impressions": 500
  },
  {
    "platform": "web",
    "text": "Polaris School Of Technology | Eligibility : Admission | College Review",
    "url": "https://www.youtube.com/watch?v=G3ojHrI6cPk",
    "date": "2026-04-19T11:53:54.086829+00:00",
    "sentiment": "neutral",
    "score": 0,
    "impressions": 1100
  },
  {
    "platform": "web",
    "text": "Polaris School of Technology - Most Awaited Campus Tour! - YouTube",
    "url": "https://www.youtube.com/watch?v=GM69qIe2_IE",
    "date": "2026-04-19T11:53:54.086841+00:00",
    "sentiment": "neutral",
    "score": 0,
    "impressions": 600
  },
  {
    "platform": "web",
    "text": "Applied AI Engineering Degree Bangalore, 4Yr BTech, No JEE",
    "url": "https://polariscampus.com/programs/applied-artificial-intelligence",
    "date": "2026-04-19T11:53:55.821302+00:00",
    "sentiment": "neutral",
    "score": 0,
    "impressions": 4500
  },
  {
    "platform": "web",
    "text": "Why an Integrated B.Tech in AI & ML with Polaris School of ...",
    "url": "https://www.msu.edu.in/blog/why-an-integrated-btech-in-ai-ml-with-polaris-school-of-technology-is-the-smartest-path-to-a-future-proof-tech-career",
    "date": "2026-04-19T11:53:55.821307+00:00",
    "sentiment": "neutral",
    "score": 0,
    "impressions": 2800
  },
  {
    "platform": "web",
    "text": "Is the Applied AI B.Tech at Polaris a serious degree or just regular ...",
    "url": "https://www.quora.com/Is-the-Applied-AI-B-Tech-at-Polaris-a-serious-degree-or-just-regular-CS-with-an-AI-label",
    "date": "2026-04-19T11:53:55.821312+00:00",
    "sentiment": "neutral",
    "score": 0,
    "impressions": 1900
  },
  {
    "platform": "web",
    "text": "B.Tech CSE in Applied Artificial Intelligence at Polaris School of ...",
    "url": "https://www.shiksha.com/college/polaris-school-of-technology-electronic-city-bangalore-238876/course-b-tech-cse-in-applied-artificial-intelligence-1471220",
    "date": "2026-04-19T11:53:55.821316+00:00",
    "sentiment": "neutral",
    "score": 0,
    "impressions": 1400
  },
  {
    "platform": "web",
    "text": "Polaris School of Technology Honest Review | BTech in CS AI/ML",
    "url": "https://www.youtube.com/watch?v=aID4GzLX80A",
    "date": "2026-04-19T11:53:55.821320+00:00",
    "sentiment": "neutral",
    "score": 0,
    "impressions": 1100
  },
  {
    "platform": "web",
    "text": "B.Tech in Computer Science & Engineering (AI/ML) - WISE",
    "url": "https://wise.msu.edu.in/b-tech-in-computer-science-engineering-ai-ml/",
    "date": "2026-04-19T11:53:55.821333+00:00",
    "sentiment": "neutral",
    "score": 0,
    "impressions": 600
  },
  {
    "platform": "web",
    "text": "Polaris School of Technology|B.Tech in CS AI & ML - YouTube",
    "url": "https://www.youtube.com/watch?v=zCN3wdo7Atw",
    "date": "2026-04-19T11:53:55.821337+00:00",
    "sentiment": "neutral",
    "score": 0,
    "impressions": 500
  },
  {
    "platform": "web",
    "text": "PST Bangalore Review | PST vs VIT vs MIT | JEE , Class 12 - YouTube",
    "url": "https://www.youtube.com/watch?v=suSPRClXm08",
    "date": "2026-04-19T11:53:57.559959+00:00",
    "sentiment": "neutral",
    "score": 0,
    "impressions": 1900
  },
  {
    "platform": "web",
    "text": "Converting PST to Bangalore Time - World Time Buddy",
    "url": "https://www.worldtimebuddy.com/pst-to-india-bangalore",
    "date": "2026-04-19T11:53:57.559967+00:00",
    "sentiment": "neutral",
    "score": 0,
    "impressions": 1100
  },
  {
    "platform": "web",
    "text": "Polaris School of Technology, Bangalore ... - CLICKTODAY WEBSITE",
    "url": "https://clicktoday.in/polaris-school-of-technology-bangalore/",
    "date": "2026-04-19T11:53:57.559975+00:00",
    "sentiment": "neutral",
    "score": 0,
    "impressions": 750
  },
  {
    "platform": "web",
    "text": "Life at Polaris. Whitefield, Bangalore. . . . . Edited by @_ ... - Instagram",
    "url": "https://www.instagram.com/reel/DOvQYGODedx/",
    "date": "2026-04-19T11:53:57.559979+00:00",
    "sentiment": "neutral",
    "score": 0,
    "impressions": 600
  },
  {
    "platform": "web",
    "text": "Polaris School of Technology - Only Education | Choose one wisely",
    "url": "https://www.onlyeducation.in/university/polaris-school-of-technology-pst-bangalore",
    "date": "2026-04-19T11:53:57.559983+00:00",
    "sentiment": "neutral",
    "score": 0,
    "impressions": 500
  }
]